pymapme/__init__.py
pymapme/exceptions.py
pymapme/models/__init__.py
pymapme/models/mapping.py
pymapme/py.typed
pymapme/utils.py
pymapme-1.0.0.dist-info/LICENSE
pymapme-1.0.0.dist-info/METADATA
pymapme-1.0.0.dist-info/WHEEL
pymapme-1.0.0.dist-info/RECORD
