Metadata-Version: 2.3
Name: pymapme
Version: 1.0.0
Summary: Transform Pydantic models from one structure to another with declarative field mapping.
License: GPL-3.0-or-later
Keywords: pydantic,mapping,transformation,data,model
Author: funnydman
Requires-Python: >=3.13,<4.0
Classifier: Development Status :: 5 - Production/Stable
Classifier: Intended Audience :: Developers
Classifier: License :: OSI Approved :: GNU General Public License v3 or later (GPLv3+)
Classifier: Operating System :: OS Independent
Classifier: Programming Language :: Python :: 3
Classifier: Programming Language :: Python :: 3.13
Classifier: Topic :: Software Development :: Libraries :: Python Modules
Classifier: Topic :: Utilities
Classifier: Typing :: Typed
Requires-Dist: pydantic (>=2.0.0,<3.0.0)
Project-URL: Bug Tracker, https://github.com/funnydman/pymapme/issues
Project-URL: Changelog, https://github.com/funnydman/pymapme/blob/main/CHANGELOG.md
Project-URL: Documentation, https://github.com/funnydman/pymapme#readme
Project-URL: Homepage, https://github.com/funnydman/pymapme
Project-URL: Repository, https://github.com/funnydman/pymapme
